benchify_maxvonhippel/__init__.py
benchify_maxvonhippel/main.py
benchify_maxvonhippel-0.0.1.dist-info/METADATA
benchify_maxvonhippel-0.0.1.dist-info/WHEEL
benchify_maxvonhippel-0.0.1.dist-info/licenses/LICENSE
benchify_maxvonhippel-0.0.1.dist-info/RECORD
