Metadata-Version: 2.1
Name: benchify_maxvonhippel
Version: 0.0.1
Summary: Formal code intelligence
Project-URL: Homepage, https://github.com/Benchify/benchify-api
Project-URL: Issues, https://github.com/Benchify/benchify-api/issues
Author-email: Max von Hippel <max@benchify.ai>, Juan Castaño <juan@benchify.ai>
License-File: LICENSE
Classifier: License :: OSI Approved :: MIT License
Classifier: Operating System :: OS Independent
Classifier: Programming Language :: Python :: 3
Requires-Python: >=3.8
